hive_builder/__init__.py
hive_builder/hive-completion.sh
hive_builder/hive.py
hive_builder/lib/azure_rm_storageshare.py
hive_builder/lib/hive_vagrant.py
hive_builder/playbooks/build-images.yml
hive_builder/playbooks/build-infra.yml
hive_builder/playbooks/build-networks.yml
hive_builder/playbooks/build-volumes.yml
hive_builder/playbooks/builtin_roles/addon/tasks/main.yml
hive_builder/playbooks/builtin_roles/addon2/tasks/main.yml
hive_builder/playbooks/builtin_roles/hive-certificate/files/extfile.cnf
hive_builder/playbooks/builtin_roles/hive-certificate/tasks/main.yml
hive_builder/playbooks/builtin_roles/hive-syslog/tasks/main.yml
hive_builder/playbooks/builtin_roles/hive-syslog/templates/transfer.conf.j2
hive_builder/playbooks/builtin_roles/hive-trust-ca/tasks/main.yml
hive_builder/playbooks/builtin_roles/hive-trust-ca-alpine/tasks/main.yml
hive_builder/playbooks/builtin_roles/hive-trust-ca-alpine/vars/main.yml
hive_builder/playbooks/builtin_roles/hive-trust-ca-centos/tasks/main.yml
hive_builder/playbooks/builtin_roles/hive-trust-ca-centos/vars/main.yml
hive_builder/playbooks/builtin_roles/hive-trust-ca-ubuntu/tasks/main.yml
hive_builder/playbooks/builtin_roles/hive-trust-ca-ubuntu/vars/main.yml
hive_builder/playbooks/builtin_roles/python-aptk/tasks/main.yml
hive_builder/playbooks/deploy-services.yml
hive_builder/playbooks/group_vars/hosts.yml
hive_builder/playbooks/group_vars/mother.yml
hive_builder/playbooks/initialize-services.yml
hive_builder/playbooks/iptables.yml
hive_builder/playbooks/push-image.yml
hive_builder/playbooks/roles/aws/tasks/build-aws.yml
hive_builder/playbooks/roles/aws/tasks/create_instance.yml
hive_builder/playbooks/roles/aws/tasks/destroy-aws.yml
hive_builder/playbooks/roles/aws/tasks/main.yml
hive_builder/playbooks/roles/aws/tasks/stop-aws.yml
hive_builder/playbooks/roles/aws/templates/aws_cli_config.j2
hive_builder/playbooks/roles/aws/templates/aws_cli_credentials.j2
hive_builder/playbooks/roles/aws/templates/azure_cli_credentials.j2
hive_builder-3.9.5.dist-info/METADATA
hive_builder-3.9.5.dist-info/WHEEL
hive_builder-3.9.5.dist-info/entry_points.txt
hive_builder-3.9.5.dist-info/licenses/LICENSE
hive_builder-3.9.5.dist-info/RECORD
