Metadata-Version: 2.4
Name: hive-builder
Version: 3.9.5
Summary: Building docker swarm environment
License: MIT
License-File: LICENSE
Author: Mitsuru Nakakawaj
Author-email: mitsuru@procube.jp
Requires-Python: >=3.9,<4.0
Classifier: License :: OSI Approved :: MIT License
Classifier: Programming Language :: Python :: 3
Classifier: Programming Language :: Python :: 3.9
Classifier: Programming Language :: Python :: 3.10
Classifier: Programming Language :: Python :: 3.11
Classifier: Programming Language :: Python :: 3.12
Classifier: Programming Language :: Python :: 3.13
Classifier: Programming Language :: Python :: 3.14
Requires-Dist: ansible-core (>=2.14.4,<3.0.0)
Requires-Dist: boto (>=2.49.0,<3.0.0)
Requires-Dist: boto3 (>=1.26.111,<2.0.0)
Requires-Dist: configparser (>=5.3.0,<6.0.0)
Requires-Dist: google-auth (>=2.17.2,<3.0.0)
Requires-Dist: lockfile (>=0.12.2,<0.13.0)
Requires-Dist: netaddr (>=1.3.0,<2.0.0)
Requires-Dist: pillow (>=10.4.0,<11.0.0)
Requires-Dist: python-vagrant (>=1.0.0,<2.0.0)
Requires-Dist: requests (>=2.28.2,<3.0.0)
